cnfc/__init__.py
cnfc/bool_lit.py
cnfc/buffer.py
cnfc/cache.py
cnfc/cardinality.py
cnfc/expr.py
cnfc/extractor.py
cnfc/formula.py
cnfc/funcs.py
cnfc/log.py
cnfc/model.py
cnfc/regex.py
cnfc/simplify.py
cnfc/tseytin.py
cnfc/tuples.py
cnfc/util.py
cnfc-0.11.0.dist-info/METADATA
cnfc-0.11.0.dist-info/WHEEL
cnfc-0.11.0.dist-info/licenses/LICENSE
cnfc-0.11.0.dist-info/RECORD
