Metadata-Version: 2.4
Name: cnfc
Version: 0.11.0
Summary: A DIMACS CNF compiler
License: Unlicense
License-File: LICENSE
Author: Aaron Windsor
Author-email: aaron.windsor@gmail.com
Requires-Python: >=3.9,<4.0
Classifier: License :: OSI Approved
Classifier: Programming Language :: Python :: 3
Classifier: Programming Language :: Python :: 3.9
Classifier: Programming Language :: Python :: 3.10
Classifier: Programming Language :: Python :: 3.11
Classifier: Programming Language :: Python :: 3.12
Classifier: Programming Language :: Python :: 3.13
Classifier: Programming Language :: Python :: 3.14
